{
  "schema_version": "std_registry_index.v1",
  "engine_version": "v7",
  "created_at": "2026-01-12T16:16:44.306407",
  "updated_at": "2026-01-12T16:16:45.241512",
  "items": [
    {
      "sku": "SKU_SMOKE_PACK_1768202175",
      "ink": "INK1",
      "active": {
        "LOW": "SKU_SMOKE_PACK_1768202175/INK1/LOW/v20260112_161644",
        "MID": "SKU_SMOKE_PACK_1768202175/INK1/MID/v20260112_161644",
        "HIGH": "SKU_SMOKE_PACK_1768202175/INK1/HIGH/v20260112_161645"
      },
      "status": "ACTIVE",
      "notes": "",
      "created_by": "SYSTEM",
      "created_at": "2026-01-12T16:16:44.306465",
      "color_mode": "aggregate",
      "expected_ink_count": 3
    }
  ]
}
