{
  "schema_version": "std_registry_index.v1",
  "engine_version": "v7",
  "created_at": "2026-01-12T16:18:02.782628",
  "updated_at": "2026-01-12T16:18:03.734612",
  "items": [
    {
      "sku": "SKU_SMOKE_PACK_1768202253",
      "ink": "INK1",
      "active": {
        "LOW": "SKU_SMOKE_PACK_1768202253/INK1/LOW/v20260112_161802",
        "MID": "SKU_SMOKE_PACK_1768202253/INK1/MID/v20260112_161803",
        "HIGH": "SKU_SMOKE_PACK_1768202253/INK1/HIGH/v20260112_161803"
      },
      "status": "ACTIVE",
      "notes": "",
      "created_by": "SYSTEM",
      "created_at": "2026-01-12T16:18:02.782797",
      "color_mode": "aggregate",
      "expected_ink_count": 3
    }
  ]
}
